setup.py
generators_to_coroutines/__init__.py
generators_to_coroutines/ast_transformers.py
generators_to_coroutines/astpp.py
generators_to_coroutines/decorators.py
generators_to_coroutines/descriptor_magic.py
generators_to_coroutines/examples.py
generators_to_coroutines/tests.py
generators_to_coroutines/tools.py
generators_to_coroutines.egg-info/PKG-INFO
generators_to_coroutines.egg-info/SOURCES.txt
generators_to_coroutines.egg-info/dependency_links.txt
generators_to_coroutines.egg-info/top_level.txt